EvilPIP/__init__.py
EvilPIP/__main__.py
xiedemo-0.0.1.dist-info/METADATA
xiedemo-0.0.1.dist-info/WHEEL
xiedemo-0.0.1.dist-info/top_level.txt
xiedemo-0.0.1.dist-info/RECORD
